neo4j_litellm/__init__.py
neo4j_litellm/data_module.py
neo4j_litellm-0.0.6.dist-info/licenses/LICENSE
neo4j_litellm-0.0.6.dist-info/METADATA
neo4j_litellm-0.0.6.dist-info/WHEEL
neo4j_litellm-0.0.6.dist-info/top_level.txt
neo4j_litellm-0.0.6.dist-info/RECORD
